maximask_and_maxitrack/__init__.py
maximask_and_maxitrack/utils.py
maximask_and_maxitrack/maximask/__init__.py
maximask_and_maxitrack/maximask/maximask.py
maximask_and_maxitrack/maximask/config/classes.flags
maximask_and_maxitrack/maximask/config/classes.priors
maximask_and_maxitrack/maximask/config/classes.thresh
maximask_and_maxitrack/maximask/model/keras_metadata.pb
maximask_and_maxitrack/maximask/model/saved_model.pb
maximask_and_maxitrack/maximask/model/variables/variables.data-00000-of-00001
maximask_and_maxitrack/maximask/model/variables/variables.index
maximask_and_maxitrack/maxitrack/__init__.py
maximask_and_maxitrack/maxitrack/maxitrack.py
maximask_and_maxitrack/maxitrack/model/keras_metadata.pb
maximask_and_maxitrack/maxitrack/model/saved_model.pb
maximask_and_maxitrack/maxitrack/model/variables/variables.data-00000-of-00001
maximask_and_maxitrack/maxitrack/model/variables/variables.index
MaxiMask-1.4.1.dist-info/LICENSE
MaxiMask-1.4.1.dist-info/METADATA
MaxiMask-1.4.1.dist-info/WHEEL
MaxiMask-1.4.1.dist-info/entry_points.txt
MaxiMask-1.4.1.dist-info/top_level.txt
MaxiMask-1.4.1.dist-info/RECORD
