Metadata-Version: 2.1
Name: MaxiMask
Version: 1.4.1
Summary: Convolutional neural networks to detect contaminants in astronomical images.
Home-page: https://github.com/mpaillassa/MaxiMask
Author: Maxime Paillassa
Author-email: maxime.paillassa@nagoya-u.jp
License: MIT
Platform: UNKNOWN
Classifier: Intended Audience :: Science/Research
Classifier: Topic :: Scientific/Engineering :: Physics
Classifier: License :: OSI Approved :: MIT License
Classifier: Programming Language :: Python :: 3.6
Classifier: Programming Language :: Python :: 3.7
Classifier: Programming Language :: Python :: 3.8
Classifier: Programming Language :: Python :: 3.9
Requires-Python: >=3.8
Requires-Dist: astropy >=5.1.1
Requires-Dist: scipy >=1.9.3
Requires-Dist: numpy >=1.23.5
Requires-Dist: tqdm >=4.62.3
Requires-Dist: tensorflow >=2.11
